{
	"US": [{
		"title": "White",
		"subtitle": "",
		"ranges": [64, 100],
		"measures": [59.3, 100],
		"markers": [64, 59.3]
	}, {
		"title": "Asian",
		"subtitle": "",
		"ranges": [4, 100],
		"measures": [25.3, 100],
		"markers": [4,25.3]
	}, {
		"title": "Latino",
		"subtitle": "",
		"ranges": [16, 100],
		"measures": [6.4, 100],
		"markers": [16,6.4]
	}, {
		"title": "Black",
		"subtitle": "",
		"ranges": [12, 100],
		"measures": [5.7, 100],
		"markers": [12,5.7]
	}, {
		"title": "Multi",
		"subtitle": "",
		"ranges": [1, 100],
		"measures": [1.56, 100],
		"markers": [1,1.56]
	}, {
		"title": "Other",
		"subtitle": "",
		"ranges": [3, 100],
		"measures": [1.4, 100],
		"markers": [3, 1.4]
	}],
	"Amazon": [{
		"title": "White",
		"subtitle": "",
		"ranges": [0, 64, 100],
		"measures": [60, 100],
		"markers": [64, 60]
	}, {
		"title": "Asian",
		"subtitle": "",
		"ranges": [0, 4, 100],
		"measures": [13, 100],
		"markers": [4, 13]
	}, {
		"title": "Latino",
		"subtitle": "",
		"ranges": [0, 16, 100],
		"measures": [9, 100],
		"markers": [16, 9]
	}, {
		"title": "Black",
		"subtitle": "",
		"ranges": [0, 12, 100],
		"measures": [15, 100],
		"markers": [12, 15]
	}, {
		"title": "Multi",
		"subtitle": "",
		"ranges": [0, 1, 100],
		"measures": [0, 100],
		"markers": [1, 0]
	}, {
		"title": "Other",
		"subtitle": "",
		"ranges": [0, 3, 100],
		"measures": [3, 100],
		"markers": [3]
	}],
	"Apple": [{
		"title": "White",
		"subtitle": "",
		"ranges": [0, 64, 100],
		"measures": [54, 100],
		"markers": [64, 54]
	}, {
		"title": "Asian",
		"subtitle": "",
		"ranges": [0, 4, 100],
		"measures": [18, 100],
		"markers": [4, 18]
	}, {
		"title": "Latino",
		"subtitle": "",
		"ranges": [0, 16, 100],
		"measures": [11, 100],
		"markers": [16, 11]
	}, {
		"title": "Black",
		"subtitle": "",
		"ranges": [0, 12, 100],
		"measures": [8, 100],
		"markers": [12, 8]
	}, {
		"title": "Multi",
		"subtitle": "",
		"ranges": [0, 1, 100],
		"measures": [2, 100],
		"markers": [1, 2]
	}, {
		"title": "Other",
		"subtitle": "",
		"ranges": [0, 3, 100],
		"measures": [1, 100],
		"markers": [3, 1]
	}],
	"Dell": [{
		"title": "White",
		"subtitle": "",
		"ranges": [0, 64, 100],
		"measures": [69, 100],
		"markers": [64, 69]
	}, {
		"title": "Asian",
		"subtitle": "",
		"ranges": [0, 4, 100],
		"measures": [9, 100],
		"markers": [4, 9]
	}, {
		"title": "Latino",
		"subtitle": "",
		"ranges": [0, 16, 100],
		"measures": [11, 100],
		"markers": [16, 11]
	}, {
		"title": "Black",
		"subtitle": "",
		"ranges": [0, 12, 100],
		"measures": [10, 100],
		"markers": [12, 10]
	}, {
		"title": "Multi",
		"subtitle": "",
		"ranges": [0, 1, 100],
		"measures": [0, 100],
		"markers": [1, 0]
	}, {
		"title": "Other",
		"subtitle": "",
		"ranges": [0, 3, 100],
		"measures": [1, 100],
		"markers": [3, 1]
	}],
	"Google": [{
		"title": "White",
		"subtitle": "",
		"ranges": [64, 100],
		"measures": [60, 100],
		"markers": [64, 60]
	}, {
		"title": "Asian",
		"subtitle": "",
		"ranges": [0, 4, 100],
		"measures": [31, 100],
		"markers": [4, 31]
	}, {
		"title": "Latino",
		"subtitle": "",
		"ranges": [0, 16, 100],
		"measures": [3, 100],
		"markers": [16, 3]
	}, {
		"title": "Black",
		"subtitle": "",
		"ranges": [0, 12, 100],
		"measures": [2, 100],
		"markers": [12, 2]
	}, {
		"title": "Multi",
		"subtitle": "",
		"ranges": [0, 1, 100],
		"measures": [3, 100],
		"markers": [1, 3]
	}, {
		"title": "Other",
		"subtitle": "",
		"ranges": [0, 3, 100],
		"measures": [0, 100],
		"markers": [3, 0]
	}],

	"Twitter": [{
		"title": "White",
		"subtitle": "",
		"ranges": [0, 64, 100],
		"measures": [59, 100],
		"markers": [64, 59]
	}, {
		"title": "Asian",
		"subtitle": "",
		"ranges": [0, 4, 100],
		"measures": [29, 100],
		"markers": [4, 29]
	}, {
		"title": "Latino",
		"subtitle": "",
		"ranges": [0, 16, 100],
		"measures": [3, 100],
		"markers": [16, 3]
	}, {
		"title": "Black",
		"subtitle": "",
		"ranges": [0, 12, 100],
		"measures": [2, 100],
		"markers": [12, 2]
	}, {
		"title": "Multi",
		"subtitle": "",
		"ranges": [0, 1, 100],
		"measures": [3, 100],
		"markers": [1, 3]
	}, {
		"title": "Other",
		"subtitle": "",
		"ranges": [0, 3, 100],
		"measures": [4, 100],
		"markers": [3, 4]
	}],
	"eBay": [{
		"title": "White",
		"subtitle": "",
		"ranges": [0, 64, 100],
		"measures": [60, 100],
		"markers": [64, 60]
	}, {
		"title": "Asian",
		"subtitle": "",
		"ranges": [0, 4, 100],
		"measures": [25, 100],
		"markers": [4, 25]
	}, {
		"title": "Latino",
		"subtitle": "",
		"ranges": [0, 16, 100],
		"measures": [5, 100],
		"markers": [16, 5]
	}, {
		"title": "Black",
		"subtitle": "",
		"ranges": [0, 12, 100],
		"measures": [8, 100],
		"markers": [12, 8]
	}, {
		"title": "Multi",
		"subtitle": "",
		"ranges": [0, 1, 100],
		"measures": [1, 100],
		"markers": [1, 1]
	}, {
		"title": "Other",
		"subtitle": "",
		"ranges": [0, 3, 100],
		"measures": [1, 100],
		"markers": [3, 1]
	}],
	"LinkedIn": [{
		"title": "White",
		"subtitle": "",
		"ranges": [0, 64, 100],
		"measures": [56, 100],
		"markers": [64, 56]
	}, {
		"title": "Asian",
		"subtitle": "",
		"ranges": [0, 4, 100],
		"measures": [37, 100],
		"markers": [4, 37]
	}, {
		"title": "Latino",
		"subtitle": "",
		"ranges": [0, 16, 100],
		"measures": [4, 100],
		"markers": [16, 4]
	}, {
		"title": "Black",
		"subtitle": "",
		"ranges": [0, 12, 100],
		"measures": [2, 100],
		"markers": [12, 2]
	}, {
		"title": "Multi",
		"subtitle": "",
		"ranges": [0, 1, 100],
		"measures": [1, 100],
		"markers": [1, 1]
	}, {
		"title": "Other",
		"subtitle": "",
		"ranges": [0, 3, 100],
		"measures": [0, 100],
		"markers": [3, 0]
	}],
	"Facebook": [{
		"title": "White",
		"subtitle": "",
		"ranges": [0, 64, 100],
		"measures": [55, 100],
		"markers": [64, 55]
	}, {
		"title": "Asian",
		"subtitle": "",
		"ranges": [0, 4, 100],
		"measures": [36, 100],
		"markers": [4, 36]
	}, {
		"title": "Latino",
		"subtitle": "",
		"ranges": [0, 16, 100],
		"measures": [4, 100],
		"markers": [16, 4]
	}, {
		"title": "Black",
		"subtitle": "",
		"ranges": [0, 12, 100],
		"measures": [2, 100],
		"markers": [12, 2]
	}, {
		"title": "Multi",
		"subtitle": "",
		"ranges": [0, 1, 100],
		"measures": [3, 100],
		"markers": [1, 3]
	}, {
		"title": "Other",
		"subtitle": "",
		"ranges": [0, 3, 100],
		"measures": [0, 100],
		"markers": [0]
	}],
	"Microsoft": [{
		"title": "White",
		"subtitle": "",
		"ranges": [0, 64, 100],
		"measures": [59, 100],
		"markers": [64, 59]
	}, {
		"title": "Asian",
		"subtitle": "",
		"ranges": [0, 4, 100],
		"measures": [29, 100],
		"markers": [4, 29]
	}, {
		"title": "Latino",
		"subtitle": "",
		"ranges": [0, 16, 100],
		"measures": [5, 100],
		"markers": [16, 5]
	}, {
		"title": "Black",
		"subtitle": "",
		"ranges": [0, 12, 100],
		"measures": [4, 100],
		"markers": [12, 4]
	}, {
		"title": "Multi",
		"subtitle": "",
		"ranges": [0, 1, 100],
		"measures": [1, 100],
		"markers": [1, 1]
	}, {
		"title": "Other",
		"subtitle": "",
		"ranges": [0, 3, 100],
		"measures": [1, 100],
		"markers": [3, 1]
	}],
	"Intel": [{
		"title": "White",
		"subtitle": "",
		"ranges": [0, 64, 100],
		"measures": [61, 100],
		"markers": [64, 61]
	}, {
		"title": "Asian",
		"subtitle": "",
		"ranges": [0, 4, 100],
		"measures": [26, 100],
		"markers": [4, 26]
	}, {
		"title": "Latino",
		"subtitle": "",
		"ranges": [0, 16, 100],
		"measures": [9, 100],
		"markers": [16, 9]
	}, {
		"title": "Black",
		"subtitle": "",
		"ranges": [0, 12, 100],
		"measures": [4, 100],
		"markers": [12, 4]
	}, {
		"title": "Multi",
		"subtitle": "",
		"ranges": [0, 1, 100],
		"measures": [0, 100],
		"markers": [1, 0]
	}, {
		"title": "Other",
		"subtitle": "",
		"ranges": [0, 3, 100],
		"measures": [1, 100],
		"markers": [3, 1]
	}]

}